Workbook

Sheet 1_Executive_Summary
A1: CYMBAL AEROSPACE CORPORATION — CLM DEVIATION MATRIX (BA-2026-AV-8921)
A2: Metadata Field | B2: Value
A3: Deal ID | B3: BA-2026-AV-8921
A4: Buyer (Prime OEM) | B4: Cymbal Aerospace Corporation
A5: Supplier / Vendor Name | B5: Apex AeroSystems Inc.
A6: Supplier Tier | B6: Tier-1 Avionics
A7: Aircraft Program | B7: 787 / 737-MAX Flight Control Display Units (FCC-900)
A8: Contract Value (USD) | B8: 45000000
A9: Tier-1 Liability Cap Multiple | B9: 2
A10: Tier-1 Liability Cap Ceiling (USD) | B10: =B8*B9
A11: Proforma Stack | B11: Cymbal GP1 (General Provisions) + SP3 (International/Tax) + SP5 (Cyber/DFARS)
A12: Pricing Model | B12: Firm-Fixed-Price (FFP) — $45,000,000 Ceiling
A13: SOW Cap Clause Reference | B13: GP1 §3.1
A14: Overall Deal Status | B14: READY_FOR_DISPATCH
A15: Total Clauses Parsed | B15: =COUNTA('2_Clause_Deviation_Matrix'!A2:A13)
A16: Untouched Clauses Count | B16: =COUNTIF('2_Clause_Deviation_Matrix'!F2:F13,"NO")
A17: Redlined Clauses Count | B17: =COUNTIF('2_Clause_Deviation_Matrix'!F2:F13,"YES")
A18: Approved Redlined Clauses Count | B18: =COUNTIFS('2_Clause_Deviation_Matrix'!F2:F13,"YES",'2_Clause_Deviation_Matrix'!G2:G13,"APPROVED")
A19: Active Cross-Clause Conflicts | B19: =COUNTA('3_Cross_Clause_Conflict_Log'!A2:A20)
A20: M365 SharePoint Folder Link | B20: https://36zrbd.sharepoint.com/sites/CymbalAerospace/Shared%20Documents/BA-2026-AV-8921
A21: SharePoint Deviation Matrix File | B21: BA-2026-AV-8921_SharePoint_Deviation_Matrix.xlsx
A22: BigQuery Dataset | B22: vertex-ai-demos-468803.boeing_clm
A23: Last Updated (UTC) | B23: 2026-10-28T04:07:32.683256+00:00

Sheet 2_Clause_Deviation_Matrix
A1: Clause ID | B1: Proforma | C1: Section Ref | D1: Clause Title | E1: SME Team | F1: Redlined? | G1: SME Status | H1: SME Owner | I1: Risk Level | J1: Regulatory Flag | K1: Boeing Baseline | L1: Vendor Redline | M1: Vendor Comment | N1: Selected Option | O1: Selected Counter-Position | P1: Reviewer | Q1: SME Rationale
A2: GP1-01 | B2: GP1 | C2: GP1 §1.1 | D2: Definitions & Order of Precedence | E2: PROCUREMENT | F2: NO | G2: UNTOUCHED | H2: Procurement & Subcontracts | I2: NONE | J2: Boeing Corporate GP1 Standard | K2: 1.1 Buyer means The Boeing Company or its wholly-owned subsidiary identified on the face of the Contract. Seller means the legal entity contracting with Buyer. In the event of any inconsistency among Contract documents, Special Provisions (SP) shall take precedence over General Provisions (GP1), excluding Firm-Fixed-Price caps set forth in GP1 §3.1. | L2: 1.1 Buyer means The Boeing Company or its wholly-owned subsidiary identified on the face of the Contract. Seller means the legal entity contracting with Buyer. In the event of any inconsistency among Contract documents, Special Provisions (SP) shall take precedence over General Provisions (GP1), excluding Firm-Fixed-Price caps set forth in GP1 §3.1. | N2: hold_firm | O2: 1.1 Buyer means The Boeing Company or its wholly-owned subsidiary identified on the face of the Contract. Seller means the legal entity contracting with Buyer. In the event of any inconsistency among Contract documents, Special Provisions (SP) shall take precedence over General Provisions (GP1), excluding Firm-Fixed-Price caps set forth in GP1 §3.1. | P2: Auto-Verified (No Redline) | Q2: Clause matches Boeing Proforma GP1/SP baseline with zero Track Changes.
A3: GP1-03 | B3: GP1 | C3: GP1 §3.1 | D3: Firm-Fixed-Price SOW Cap & Pricing Integrity | E3: PROCUREMENT | F3: NO | G3: UNTOUCHED | H3: Procurement & Cost Management | I3: NONE | J3: Firm-Fixed-Price SOW Lock | K3: 3.1 Unless expressly modified by a bilateral Change Order signed by Buyer's Authorized Procurement Representative referencing this GP1 §3.1, all unit prices in Statement of Work (SOW) Schedule A are Firm-Fixed-Price (FFP) and shall not be subject to uncapped surcharges, tariff pass-throughs, or raw material indexing. | L3: 3.1 Unless expressly modified by a bilateral Change Order signed by Buyer's Authorized Procurement Representative referencing this GP1 §3.1, all unit prices in Statement of Work (SOW) Schedule A are Firm-Fixed-Price (FFP) and shall not be subject to uncapped surcharges, tariff pass-throughs, or raw material indexing. | N3: hold_firm | O3: 3.1 Unless expressly modified by a bilateral Change Order signed by Buyer's Authorized Procurement Representative referencing this GP1 §3.1, all unit prices in Statement of Work (SOW) Schedule A are Firm-Fixed-Price (FFP) and shall not be subject to uncapped surcharges, tariff pass-throughs, or raw material indexing. | P3: Auto-Verified (No Redline) | Q3: Clause matches Boeing Proforma GP1/SP baseline with zero Track Changes.
A4: GP1-05 | B4: GP1 | C4: GP1 §5.2 | D4: Packing, Marking & Aerospace Preservation | E4: ENGINEERING | F4: NO | G4: UNTOUCHED | H4: Supplier Logistics & Packaging | I4: NONE | J4: ATA Spec 300 / D6-81628 | K4: 5.2 Seller shall pack, mark, and ship all Goods in accordance with Boeing Document D6-81628 and ATA Spec 300 electro-static discharge (ESD) protection standards for Class 1 flight-critical avionics. | L4: 5.2 Seller shall pack, mark, and ship all Goods in accordance with Boeing Document D6-81628 and ATA Spec 300 electro-static discharge (ESD) protection standards for Class 1 flight-critical avionics. | N4: hold_firm | O4: 5.2 Seller shall pack, mark, and ship all Goods in accordance with Boeing Document D6-81628 and ATA Spec 300 electro-static discharge (ESD) protection standards for Class 1 flight-critical avionics. | P4: Auto-Verified (No Redline) | Q4: Clause matches Boeing Proforma GP1/SP baseline with zero Track Changes.
A5: GP1-07 | B5: GP1 | C5: GP1 §7.1 | D5: Quality Management System (AS9100 Rev D) | E5: ENGINEERING | F5: NO | G5: UNTOUCHED | H5: Supplier Quality Assurance | I5: NONE | J5: AS9100 Rev D / D6-82479 | K5: 7.1 Seller shall maintain an accredited AS9100 Rev D Quality Management System and comply with Boeing Quality Management System Requirements for Suppliers (D6-82479) throughout Contract performance. | L5: 7.1 Seller shall maintain an accredited AS9100 Rev D Quality Management System and comply with Boeing Quality Management System Requirements for Suppliers (D6-82479) throughout Contract performance. | N5: hold_firm | O5: 7.1 Seller shall maintain an accredited AS9100 Rev D Quality Management System and comply with Boeing Quality Management System Requirements for Suppliers (D6-82479) throughout Contract performance. | P5: Auto-Verified (No Redline) | Q5: Clause matches Boeing Proforma GP1/SP baseline with zero Track Changes.
A6: GP1-09 | B6: GP1 | C6: GP1 §9.1 | D6: Changes & Equitable Adjustment | E6: PROCUREMENT | F6: NO | G6: UNTOUCHED | H6: Procurement & Subcontracts | I6: NONE | J6: Boeing Corporate GP1 Standard | K6: 9.1 Buyer's Authorized Procurement Representative may at any time, by written order, direct changes within the general scope of this Contract in drawings, designs, specifications, or delivery schedules. | L6: 9.1 Buyer's Authorized Procurement Representative may at any time, by written order, direct changes within the general scope of this Contract in drawings, designs, specifications, or delivery schedules. | N6: hold_firm | O6: 9.1 Buyer's Authorized Procurement Representative may at any time, by written order, direct changes within the general scope of this Contract in drawings, designs, specifications, or delivery schedules. | P6: Auto-Verified (No Redline) | Q6: Clause matches Boeing Proforma GP1/SP baseline with zero Track Changes.
A7: GP1-12 | B7: GP1 | C7: GP1 §12.2 | D7: Warranty & FAA Source Inspection | E7: ENGINEERING | F7: YES | G7: APPROVED | H7: Engineering & QA (FAA DER) | I7: HIGH | J7: FAA 14 CFR Part 21 Lockout | K7: 12.2 Seller warrants all Goods against defects in material, workmanship, and avionics firmware for thirty-six (36) months from initial aircraft delivery to Boeing's airline customer. Boeing and FAA representatives may conduct unannounced source inspections at Seller's facility at any time to verify AS9100 Rev D and FAA 14 CFR Part 21 production airworthiness compliance. | L7: 12.2 Seller warrants all Goods against defects in material, workmanship, and avionics firmware for twelve (12) months from factory shipment. Boeing and FAA representatives may conduct scheduled inspections upon thirty (30) days prior written notice to verify AS9100 Rev D and FAA 14 CFR Part 21 production airworthiness compliance. | M7: Apex AeroSystems Legal: Our standard commercial avionics warranty is 12 months from ex-works shipment, and unannounced facility audits disrupt cleanroom assembly shifts. | N7: hold_firm | O7: 12.2 (a) Airworthiness & Hardware/Firmware Warranty: Seller warrants all Goods, including `FCC-900` flight control hardware, triplex voting channels, and embedded `DO-178C DAL-A` avionics firmware, to be free from defects in design, material, and workmanship for thirty-six (36) months from initial aircraft delivery to Cymbal Aerospace's airline customer, and Seller shall repair or replace defective flight-critical LRUs on an Aircraft-on-Ground (`AOG`) 24-hour turnaround basis at Seller's expense. (b) Regulatory Source Surveillance: Cymbal Aerospace and Federal Aviation Administration (`FAA`) representatives may conduct unannounced source inspections at Seller's facility at any time to verify `AS9100 Rev D` quality compliance, `FAA 14 CFR Part 21.140` production certificate airworthiness conformity, and sub-tier test bench calibration records. | P7: Lead Contract Owner (M. Vance) | Q7: Harmonized LOCKOUT-GP1-12-FAA across ENGINEERING (GP1-12) and ENGINEERING (GP1-12): applied Playbook harmonized resolution (hold_firm) preserving GP1-12 guardrails.
A8: GP1-15 | B8: GP1 | C8: GP1 §15.1 | D8: Termination for Convenience | E8: LEGAL | F8: NO | G8: UNTOUCHED | H8: Corporate Legal & Commercial | I8: NONE | J8: FAR 52.249-2 Aligned | K8: 15.1 Buyer may terminate all or any part of this Contract for convenience by written notice to Seller. Seller shall immediately stop all terminated work and mitigate termination settlement costs. | L8: 15.1 Buyer may terminate all or any part of this Contract for convenience by written notice to Seller. Seller shall immediately stop all terminated work and mitigate termination settlement costs. | N8: hold_firm | O8: 15.1 Buyer may terminate all or any part of this Contract for convenience by written notice to Seller. Seller shall immediately stop all terminated work and mitigate termination settlement costs. | P8: Auto-Verified (No Redline) | Q8: Clause matches Boeing Proforma GP1/SP baseline with zero Track Changes.
A9: GP1-19 | B9: GP1 | C9: GP1 §19 & §24 | D9: Limitation of Liability & IP Indemnity | E9: LEGAL | F9: YES | G9: APPROVED | H9: Corporate Legal & IP | I9: CRITICAL | J9: Corporate Legal Playbook Tier-1 | K9: 19.1 Seller's liability for direct damages, line-stoppage, and airworthiness recall costs shall be uncapped. 24.1 Seller shall indemnify Boeing against all third-party intellectual property infringement claims including system-level avionics bus integration. | L9: 19.1 Seller's liability for direct damages, line-stoppage, and airworthiness recall costs shall not exceed one hundred percent (100%) of the total Purchase Order value ($45M). 24.1 Seller shall indemnify Boeing against all third-party intellectual property infringement claims except where such claim arises from combination of Goods with any Boeing or third-party flight control bus. | M9: Apex AeroSystems Legal: Board risk policy requires a 1x PO liability cap ($45M) and standard commercial carveout for system-combination IP claims. | N9: compromise_tier_1 | O9: 19.1 (a) Direct, Line-Stoppage & Airworthiness Recall Liability: Seller's liability for general direct damages and final assembly line-stoppage shall be capped at two hundred percent (200%) of the total Purchase Order value ($90M), provided that liability for Fleet Airworthiness Directive (`AD`) recall, gross negligence, willful misconduct, and §24 IP indemnification shall remain strictly uncapped. 24.1 (b) Intellectual Property Indemnification: Seller shall defend, indemnify, and hold harmless Cymbal Aerospace and its airline customers against all third-party intellectual property infringement claims including system-level avionics bus integration, except where such claim arises solely from Cymbal Aerospace's proprietary flight control bus specifications. | P9: Elena Rostova, J.D. (Senior Counsel, Commercial & IP) | Q9: Applied Playbook Tier-1 Compromise (69% historical precedent across 11/16 Tier-1 avionics deals): 2x PO ($90M) super-cap on general direct damages while holding uncapped liability for airworthiness recall and IP indemnity, narrowing the IP carveout strictly to Cymbal Aerospace proprietary bus specifications.
A10: GP1-28 | B10: GP1 | C10: GP1 §28.1 | D10: Governing Law & Dispute Resolution | E10: LEGAL | F10: NO | G10: UNTOUCHED | H10: Corporate Legal | I10: NONE | J10: Delaware / Washington Law Standard | K10: 28.1 This Contract and all disputes arising hereunder shall be governed by and construed in accordance with the laws of the State of Delaware, excluding its conflict of laws rules. | L10: 28.1 This Contract and all disputes arising hereunder shall be governed by and construed in accordance with the laws of the State of Delaware, excluding its conflict of laws rules. | N10: hold_firm | O10: 28.1 This Contract and all disputes arising hereunder shall be governed by and construed in accordance with the laws of the State of Delaware, excluding its conflict of laws rules. | P10: Auto-Verified (No Redline) | Q10: Clause matches Boeing Proforma GP1/SP baseline with zero Track Changes.
A11: SP3-02 | B11: SP3 | C11: SP3 §2.1 | D11: Export Compliance (ITAR & EAR) | E11: TAX | F11: NO | G11: UNTOUCHED | H11: Global Trade Controls | I11: NONE | J11: 22 CFR 120-130 (ITAR) / 15 CFR 730-774 (EAR) | K11: 2.1 Seller shall comply with all applicable U.S. export control laws and regulations, including the International Traffic in Arms Regulations (ITAR) and Export Administration Regulations (EAR). | L11: 2.1 Seller shall comply with all applicable U.S. export control laws and regulations, including the International Traffic in Arms Regulations (ITAR) and Export Administration Regulations (EAR). | N11: hold_firm | O11: 2.1 Seller shall comply with all applicable U.S. export control laws and regulations, including the International Traffic in Arms Regulations (ITAR) and Export Administration Regulations (EAR). | P11: Auto-Verified (No Redline) | Q11: Clause matches Boeing Proforma GP1/SP baseline with zero Track Changes.
A12: SP3-04 | B12: SP3 | C12: SP3 §4.1 | D12: Customs, Duties & International Tariffs | E12: TAX | F12: YES | G12: APPROVED | H12: Global Tax & Trade | I12: MOD | J12: Cross-Clause SOW §3.1 Dependency | K12: 4.1 All unit prices are DDP (Incoterms 2020) Boeing Everett/Renton facility and inclusive of all import duties, customs fees, and tariffs. | L12: 4.1 All unit prices are exclusive of any new or increased Section 232/301 tariffs on titanium forgings or semiconductor wafers exceeding five percent (5%), which shall be passed through 100% to Boeing. | M12: Apex AeroSystems Tax: Due to volatile Section 232/301 duties on European titanium and Taiwanese wafers, Seller requires 100% pass-through of tariff increases above 5%. | N12: custom_harmonized | O12: 4.1 (a) Importer of Record & Customs Clearance: Seller shall act as Importer of Record for all imported sub-tier components, raw aerospace titanium forgings, and radiation-hardened semiconductor wafers. (b) Tariff & Duty Allocation: All unit prices in Statement of Work (`SOW-AV-8921`) Schedule A are DDP (Incoterms 2020) Cymbal Aerospace Everett/Renton facility. Any verified new Section 232/301 tariff increase exceeding 5.0% on raw titanium forgings or semiconductor wafers shall be shared 50/50 between Cymbal Aerospace and Seller, strictly capped at a maximum aggregate adjustment of 2.0% of the GP1 §3.1 Firm-Fixed-Price SOW unit price. | P12: Lead Contract Owner (M. Vance) | Q12: Harmonized CONFLICT-SP3-04-GP1-03 across TAX (SP3-04) and PROCUREMENT (GP1-03): applied Playbook harmonized resolution (custom_harmonized) preserving GP1-03 guardrails.
A13: SP5-03 | B13: SP5 | C13: SP5 §3.2 | D13: Cybersecurity Incident Reporting (DFARS) | E13: CYBER | F13: YES | G13: APPROVED | H13: Supplier Cyber Defense | I13: HIGH | J13: DFARS 252.204-7012 Lockout | K13: 3.2 Seller shall maintain NIST SP 800-171 controls and report any cybersecurity incident affecting Boeing Covered Defense Information or technical data within seventy-two (72) hours of discovery, and provide forensic log images upon request. | L13: 3.2 Seller shall maintain NIST SP 800-171 controls and report any cybersecurity incident affecting Boeing Covered Defense Information or technical data within ten (10) business days following confirmation of a material breach, and provide forensic log images upon request. | M13: Apex AeroSystems CISO: Our SOC requires 10 business days to validate root-cause forensics before external customer notification. | N13: hold_firm | O13: 3.2 (a) CUI Safeguards & NIST SP 800-171 Rev 2 Compliance: Seller shall maintain an accredited Cybersecurity Maturity Model Certification (`CMMC 2.0 Level 2`) posture and implement all 110 security controls in `NIST SP 800-171 Rev 2` across all engineering networks storing or processing Cymbal Aerospace Covered Defense Information (`CDI`), Controlled Unclassified Information (`CUI`), or `FCC-900` flight control source code. (b) Mandatory Cyber Incident Reporting & Forensics: Pursuant to `DoD DFARS 252.204-7012`, Seller shall report any cybersecurity incident affecting Cymbal Aerospace CDI or technical data to Buyer's Cyber Security Operations Center (`CSOC`) and the DoD DIBNet portal within seventy-two (72) hours of discovery, preserve affected system media for ninety (90) days, and provide raw forensic log images and malware telemetry upon request. | P13: Lead Contract Owner (M. Vance) | Q13: Harmonized LOCKOUT-SP5-03-DFARS across CYBER (SP5-03) and CYBER (SP5-03): applied Playbook harmonized resolution (hold_firm) preserving SP5-03 guardrails.

Sheet 3_Cross_Clause_Conflict_Log
A1: Rule ID | B1: Rule Type | C1: Source Clause | D1: Target Clause | E1: Severity | F1: Conflict Title | G1: Description | H1: Harmonized Resolution
A21: Immutable Governance Audit Trail
A22: Event ID | B22: Created At (UTC) | C22: Deal ID | D22: Clause ID | E22: SME Team | F22: Actor | G22: Action | H22: Selected Option Key | I22: Source Surface | J22: Rationale
A23: EVT-3858F13A | B23: 2026-10-28T04:07:31.289702+00:00 | C23: BA-2026-AV-8921 | D23: SP3-04 | E23: TAX | F23: Lead Contract Owner (M. Vance) | G23: CONFLICT_HARMONIZED | H23: custom_harmonized | I23: GEMINI_AGENT_MCP | J23: Harmonized CONFLICT-SP3-04-GP1-03 across TAX (SP3-04) and PROCUREMENT (GP1-03): applied Playbook harmonized resolution (custom_harmonized) preserving GP1-03 guardrails.
A24: EVT-915DC062 | B24: 2026-10-28T04:07:21.428139+00:00 | C24: BA-2026-AV-8921 | D24: SP3-04 | E24: TAX | F24: Marcus Chen, CPA (Director, Global Tax & Trade) | G24: CONFLICT_TRIGGERED | H24: accept_vendor | I24: GEMINI_AGENT_MCP | J24: Accepting uncapped >5% tariff pass-through to expedite delivery.
A25: EVT-EDC85FDA | B25: 2026-10-28T04:07:13.853667+00:00 | C25: BA-2026-AV-8921 | D25: SP5-03 | E25: CYBER | F25: Lead Contract Owner (M. Vance) | G25: CONFLICT_HARMONIZED | H25: hold_firm | I25: GEMINI_AGENT_MCP | J25: Harmonized LOCKOUT-SP5-03-DFARS across CYBER (SP5-03) and CYBER (SP5-03): applied Playbook harmonized resolution (hold_firm) preserving SP5-03 guardrails.
A26: EVT-5CEE1E79 | B26: 2026-10-28T04:07:02.010819+00:00 | C26: BA-2026-AV-8921 | D26: GP1-12 | E26: ENGINEERING | F26: Lead Contract Owner (M. Vance) | G26: CONFLICT_HARMONIZED | H26: hold_firm | I26: GEMINI_AGENT_MCP | J26: Harmonized LOCKOUT-GP1-12-FAA across ENGINEERING (GP1-12) and ENGINEERING (GP1-12): applied Playbook harmonized resolution (hold_firm) preserving GP1-12 guardrails.
A27: EVT-EBC32F11 | B27: 2026-10-28T04:06:52.560277+00:00 | C27: BA-2026-AV-8921 | D27: SP5-03 | E27: CYBER | F27: Adversarial Tester (Cyber) | G27: CONFLICT_TRIGGERED | H27: accept_vendor | I27: GEMINI_AGENT_MCP | J27: Attempting to accept 10 business day cyber reporting window.
A28: EVT-880D7540 | B28: 2026-10-28T04:06:44.366674+00:00 | C28: BA-2026-AV-8921 | D28: GP1-12 | E28: ENGINEERING | F28: Adversarial Tester (Engineering) | G28: CONFLICT_TRIGGERED | H28: accept_vendor | I28: GEMINI_AGENT_MCP | J28: Attempting to accept 12-month warranty and 30-day scheduled inspection notice.
A29: EVT-B1DCD890 | B29: 2026-10-28T04:06:35.602301+00:00 | C29: BA-2026-AV-8921 | D29: ALL | E29: PROCUREMENT | F29: Lead Contract Owner (M. Vance) | G29: INGESTED_REDLINE | H29: hold_firm | I29: GEMINI_AGENT_MCP | J29: Deterministic OOXML Track Changes extraction persisted to BigQuery deal_clause_deviations.
A30: EVT-8921-005 | B30: 2026-10-28T04:04:26.616643+00:00 | C30: BA-2026-AV-8921 | D30: SP5-03 | E30: CYBER | F30: Capt. Devon Brooks (Lead, Supplier Cyber Defense) | G30: SME_APPROVED | H30: hold_firm | I30: EXPERIENCE_LAYER_UI | J30: Held firm on 72-hour incident notification. DFARS 252.204-7012 and NIST SP 800-171 impose a non-negotiable 72-hour DoD reporting window (94% held firm across 15/16 historical contracts).
A31: EVT-8921-004 | B31: 2026-10-28T04:00:26.616643+00:00 | C31: BA-2026-AV-8921 | D31: SP3-04 | E31: TAX | F31: Marcus Chen, CPA (Director, Global Tax & Trade) | G31: CONFLICT_TRIGGERED | H31: accept_vendor | I31: GEMINI_AGENT_MCP | J31: Accepted vendor >5% Section 232/301 titanium and wafer tariff pass-through to avoid Q3 avionics delivery delay, pending Procurement verification against SOW cap.
A32: EVT-8921-003 | B32: 2026-10-28T03:56:26.616643+00:00 | C32: BA-2026-AV-8921 | D32: GP1-19 | E32: LEGAL | F32: Elena Rostova, J.D. (Senior Counsel, Commercial & IP) | G32: SME_APPROVED | H32: compromise_tier_1 | I32: EXPERIENCE_LAYER_UI | J32: Applied Playbook Tier-1 Compromise (69% historical precedent across 11/16 Tier-1 avionics deals): 2x PO ($90M) super-cap on general direct damages while holding uncapped liability for airworthiness recall and IP indemnity, narrowing the IP carveout strictly to Cymbal Aerospace proprietary bus specifications.
A33: EVT-8921-002 | B33: 2026-10-28T03:52:26.616643+00:00 | C33: BA-2026-AV-8921 | D33: GP1-12 | E33: ENGINEERING | F33: Dr. Aris Thorne (Principal FAA DER, Flight Controls QA) | G33: SME_APPROVED | H33: hold_firm | I33: EXPERIENCE_LAYER_UI | J33: Rejected vendor 12-month warranty and 30-day inspection notice. FAA 14 CFR Part 21.140 and AS9100 Rev D mandate unannounced source inspection access at all times. Precedent shows 88% (14/16) held firm.
A34: EVT-8921-001 | B34: 2026-10-28T03:41:26.616643+00:00 | C34: BA-2026-AV-8921 | D34: ALL | E34: PROCUREMENT | F34: Lead Contract Owner (M. Vance) | G34: INGESTED_REDLINE | H34: hold_firm | I34: GEMINI_AGENT_MCP | J34: Deterministic OOXML Track Changes extraction completed against Cymbal_GP1_Standard.docx.

Sheet 4_BigQuery_Precedent_Benchmarks
A1: Clause ID | B1: Section Ref | C1: SME Team | D1: Regulatory Lockout | E1: Held Firm Count | F1: Compromise Tier-1 Count | G1: Accepted Vendor Count | H1: Total Matched Precedents | I1: Held Firm % | J1: Compromise Tier-1 % | K1: Accepted Vendor % | L1: Precedent Exception ID | M1: Historical Contract ID | N1: Supplier Name | O1: Supplier Tier | P1: Boeing Program | Q1: Outcome Category | R1: Similarity Score | S1: Approval Authority | T1: Signed Date | U1: Final Agreed Language | V1: Negotiation Notes
A2: GP1-12 | B2: GP1 §12.2 | C2: ENGINEERING | D2: LOCKED | E2: 14 | F2: 2 | G2: 0 | H2: =SUM(E2:G2) | I2: =IF(H2>0,E2/H2,0) | J2: =IF(H2>0,F2/H2,0) | K2: =IF(H2>0,G2/H2,0) | L2: EXC-GP1-12-08 | M2: BA-2024-AV-2490 | N2: L3Harris Avionics | O2: Tier-1 Avionics | P2: BDS | Q2: HELD_FIRM | R2: 0.8723 | S2: BDS Quality Director | T2: 2024-07-11 | U2: 36-month warranty from delivery; unannounced FAA and Cymbal Aerospace source inspections at any time. | V2: Mandatory FAA and DCMA unannounced audit flowdown preserved.
A3: GP1-12 | B3: GP1 §12.2 | C3: ENGINEERING | D3: LOCKED | E3: 14 | F3: 2 | G3: 0 | H3: =SUM(E3:G3) | I3: =IF(H3>0,E3/H3,0) | J3: =IF(H3>0,F3/H3,0) | K3: =IF(H3>0,G3/H3,0) | L3: EXC-GP1-12-01 | M3: BA-2025-AV-4102 | N3: Honeywell Aerospace | O3: Tier-1 Avionics | P3: 787 | Q3: HELD_FIRM | R3: 0.8592 | S3: Chief FAA DER & VP Supplier Quality | T3: 2025-11-14 | U3: Seller warrants all Goods for 36 months from aircraft delivery. Cymbal Aerospace and FAA representatives may conduct unannounced source inspections at any time under FAA 14 CFR Part 21.140. | V3: Rejected 30-day notice due to FAA 14 CFR Part 21.140 regulatory lockout; held 36-month airworthiness warranty.
A4: GP1-12 | B4: GP1 §12.2 | C4: ENGINEERING | D4: LOCKED | E4: 14 | F4: 2 | G4: 0 | H4: =SUM(E4:G4) | I4: =IF(H4>0,E4/H4,0) | J4: =IF(H4>0,F4/H4,0) | K4: =IF(H4>0,G4/H4,0) | L4: EXC-GP1-12-02 | M4: BA-2025-AV-3988 | N4: Collins Aerospace | O4: Tier-1 Avionics | P4: 737-MAX | Q4: HELD_FIRM | R4: 0.8583 | S4: Director, Flight Controls QA | T4: 2025-09-22 | U4: Seller warrants all Goods for 36 months from initial aircraft delivery. Cymbal Aerospace and FAA retain unannounced source inspection rights at Seller facilities at any time. | V4: FAA Production Certificate 700 requires unrestricted FAA/Cymbal Aerospace source surveillance.
A5: GP1-12 | B5: GP1 §12.2 | C5: ENGINEERING | D5: LOCKED | E5: 14 | F5: 2 | G5: 0 | H5: =SUM(E5:G5) | I5: =IF(H5>0,E5/H5,0) | J5: =IF(H5>0,F5/H5,0) | K5: =IF(H5>0,G5/H5,0) | L5: EXC-GP1-12-10 | M5: BA-2024-AV-1980 | N5: Crane Aerospace & Electronics | O5: Tier-1 Avionics | P5: 737-MAX | Q5: HELD_FIRM | R5: 0.8459 | S5: Supplier QA Manager | T5: 2024-03-29 | U5: 36 months warranty from aircraft delivery; unannounced Cymbal Aerospace and FAA source inspections at any time. | V5: FAA 14 CFR Part 21.140 prohibits prior notice gating.
A6: GP1-12 | B6: GP1 §12.2 | C6: ENGINEERING | D6: LOCKED | E6: 14 | F6: 2 | G6: 0 | H6: =SUM(E6:G6) | I6: =IF(H6>0,E6/H6,0) | J6: =IF(H6>0,F6/H6,0) | K6: =IF(H6>0,G6/H6,0) | L6: EXC-GP1-12-09 | M6: BA-2024-AV-2208 | N6: Curtiss-Wright Defense Solutions | O6: Tier-1 Avionics | P6: 787 | Q6: HELD_FIRM | R6: 0.841 | S6: Principal FAA DER | T6: 2024-05-15 | U6: 36 months warranty from initial aircraft delivery; unannounced source inspections at any time. | V6: Held firm on GP1 §12.2 baseline.
A7: GP1-19 | B7: GP1 §19 & §24 | C7: LEGAL | D7: ELIGIBLE | E7: 4 | F7: 11 | G7: 1 | H7: =SUM(E7:G7) | I7: =IF(H7>0,E7/H7,0) | J7: =IF(H7>0,F7/H7,0) | K7: =IF(H7>0,G7/H7,0) | L7: EXC-GP1-19-08 | M7: BA-2024-AV-2490 | N7: L3Harris Avionics | O7: Tier-1 Avionics | P7: BDS | Q7: HELD_FIRM | R7: 0.8314 | S7: BDS Chief Legal Counsel | T7: 2024-07-11 | U7: Uncapped direct damages, line-stoppage, airworthiness recall, and full system-level IP indemnity. | V7: Held firm on uncapped liability due to classified defense mission criticality.
A8: GP1-19 | B8: GP1 §19 & §24 | C8: LEGAL | D8: ELIGIBLE | E8: 4 | F8: 11 | G8: 1 | H8: =SUM(E8:G8) | I8: =IF(H8>0,E8/H8,0) | J8: =IF(H8>0,F8/H8,0) | K8: =IF(H8>0,G8/H8,0) | L8: EXC-GP1-19-03 | M8: BA-2025-AV-3710 | N8: Thales Avionics | O8: Tier-1 Avionics | P8: 777X | Q8: COMPROMISE_TIER_1 | R8: 0.8223 | S8: VP Corporate Legal | T8: 2025-08-05 | U8: 200% (2x PO) cap on general direct damages; uncapped recall, gross negligence, and IP indemnity; IP exclusion limited solely to Cymbal Aerospace proprietary specifications. | V8: Aligned with Tier-1 avionics precedent (2x PO cap + uncapped safety/IP).
A9: GP1-19 | B9: GP1 §19 & §24 | C9: LEGAL | D9: ELIGIBLE | E9: 4 | F9: 11 | G9: 1 | H9: =SUM(E9:G9) | I9: =IF(H9>0,E9/H9,0) | J9: =IF(H9>0,F9/H9,0) | K9: =IF(H9>0,G9/H9,0) | L9: EXC-GP1-19-02 | M9: BA-2025-AV-3988 | N9: Collins Aerospace | O9: Tier-1 Avionics | P9: 737-MAX | Q9: COMPROMISE_TIER_1 | R9: 0.821 | S9: Senior Counsel, Commercial & IP | T9: 2025-09-22 | U9: 200% (2x PO) super-cap on general direct damages; uncapped airworthiness recall and IP indemnity; IP carveout restricted solely to Cymbal Aerospace proprietary flight control bus specifications. | V9: Standard Tier-1 Avionics compromise per Corporate Legal Playbook.
A10: GP1-19 | B10: GP1 §19 & §24 | C10: LEGAL | D10: ELIGIBLE | E10: 4 | F10: 11 | G10: 1 | H10: =SUM(E10:G10) | I10: =IF(H10>0,E10/H10,0) | J10: =IF(H10>0,F10/H10,0) | K10: =IF(H10>0,G10/H10,0) | L10: EXC-GP1-19-01 | M10: BA-2025-AV-4102 | N10: Honeywell Aerospace | O10: Tier-1 Avionics | P10: 787 | Q10: COMPROMISE_TIER_1 | R10: 0.8204 | S10: VP Corporate Legal & Chief IP Counsel | T10: 2025-11-14 | U10: Direct damages capped at 200% (2x) of PO value ($90M equivalent), with uncapped liability for airworthiness recall, gross negligence, and IP indemnity. IP carveout narrowed solely to claims caused by Cymbal Aerospace proprietary bus specifications. | V10: Playbook Tier-1 Compromise accepted: 2x PO super-cap on general direct damages + narrowed Cymbal Aerospace-sole-spec IP carveout.
A11: GP1-19 | B11: GP1 §19 & §24 | C11: LEGAL | D11: ELIGIBLE | E11: 4 | F11: 11 | G11: 1 | H11: =SUM(E11:G11) | I11: =IF(H11>0,E11/H11,0) | J11: =IF(H11>0,F11/H11,0) | K11: =IF(H11>0,G11/H11,0) | L11: EXC-GP1-19-04 | M11: BA-2025-AV-3504 | N11: BAE Systems Controls | O11: Tier-1 Avionics | P11: 737-MAX | Q11: COMPROMISE_TIER_1 | R11: 0.8174 | S11: Deputy General Counsel | T11: 2025-06-18 | U11: 2x PO (200%) cap on general direct damages; airworthiness recall and §24 IP indemnification remain strictly uncapped; IP carveout narrowed to Cymbal Aerospace sole specifications. | V11: Protected uncapped airworthiness recall and system integration IP.
A12: SP3-04 | B12: SP3 §4.1 | C12: TAX | D12: ELIGIBLE | E12: 5 | F12: 10 | G12: 1 | H12: =SUM(E12:G12) | I12: =IF(H12>0,E12/H12,0) | J12: =IF(H12>0,F12/H12,0) | K12: =IF(H12>0,G12/H12,0) | L12: EXC-SP3-04-01 | M12: BA-2025-AV-4102 | N12: Honeywell Aerospace | O12: Tier-1 Avionics | P12: 787 | Q12: COMPROMISE_TIER_1 | R12: 0.8342 | S12: Director, Global Tax & VP Procurement | T12: 2025-11-14 | U12: Unit prices remain DDP Cymbal Aerospace Everett/Renton. Verified new Section 232/301 tariff increases >5.0% on titanium forgings or semiconductor wafers shared 50/50, strictly capped at a maximum aggregate adjustment of 2.0% of the GP1 §3.1 Firm-Fixed-Price SOW unit price. | V12: Harmonized 50/50 sharing with a hard 2.0% SOW cap to preserve GP1 §3.1 Firm-Fixed-Price integrity.
A13: SP3-04 | B13: SP3 §4.1 | C13: TAX | D13: ELIGIBLE | E13: 5 | F13: 10 | G13: 1 | H13: =SUM(E13:G13) | I13: =IF(H13>0,E13/H13,0) | J13: =IF(H13>0,F13/H13,0) | K13: =IF(H13>0,G13/H13,0) | L13: EXC-SP3-04-02 | M13: BA-2025-AV-3988 | N13: Collins Aerospace | O13: Tier-1 Avionics | P13: 737-MAX | Q13: COMPROMISE_TIER_1 | R13: 0.8283 | S13: Global Tax & Procurement Joint Sign-off | T13: 2025-09-22 | U13: 50/50 tariff sharing above 5.0% threshold, strictly capped at a maximum aggregate adjustment of 2.0% of the GP1 §3.1 Firm-Fixed-Price SOW unit price. | V13: Prevented cross-clause breach of GP1 §3.1 FFP ceiling via 2.0% aggregate cap.
... A21: SP5-03 | B21: SP5 §3.2 | C21: CYBER | D21: LOCKED | E21: 15 | F21: 1 | G21: 0 | H21: =SUM(E21:G21) | I21: =IF(H21>0,E21/H21,0) | J21: =IF(H21>0,F21/H21,0) | K21: =IF(H21>0,G21/H21,0) | L21: EXC-SP5-03-05 | M21: BA-2024-AV-2911 | N21: Moog Aircraft Group | O21: Tier-1 Actuation & Avionics | P21: 787 | Q21: COMPROMISE_TIER_1 | R21: 0.811 | S21: CISO & Supplier Cyber Defense | T21: 2024-12-03 | U21: 72-hour preliminary cyber incident notification upon discovery enforced; full root-cause forensic log packet permitted within 5 business days. | V21: Kept mandatory 72-hour initial notification intact while allowing 5 business days for deep forensic log image delivery.

Sheet 5_Portfolio_Tabular_Review
A1: Deal ID | B1: Supplier | C1: Program | D1: Value ($ USD) | E1: GP1 §12.2 Warranty & FAA Inspection | F1: GP1 §19 Limitation of Liability | G1: SP3 §4.1 Customs & Tariffs | H1: SP5 §3.2 DFARS Cyber Reporting | I1: Liability Cap Multiple | J1: Portfolio Gate Status
A2: BA-2026-AV-8921 | B2: Apex AeroSystems Inc. | C2: 787 / 737-MAX Flight Control Display Units (FCC-900) | D2: 45000000 | E2: [APPROVED] | hold_firm | 12.2 (a) Airworthiness & Hardware/Firmware Warranty: Seller warrants all Goods, including `FCC-900` flight control hardware, triplex voting channels, and embedded `DO-178C DAL-A` avionics firmware, to be free from defects in design, material, and workmanship for thirty-six (36) months from initial aircraft delivery to Cymbal Aerospace's airline customer, and Seller shall repair or replace defective flight-critical LRUs on an Aircraft-on-Ground (`AOG`) 24-hour turnaround basis at Seller's expense. (b) Regulatory Source Surveillance: Cymbal Aerospace and Federal Aviation Administration (`FAA`) representatives may conduct unannounced source inspections at Seller's facility at any time to verify `AS9100 Rev D` quality compliance, `FAA 14 CFR Part 21.140` production certificate airworthiness conformity, and sub-tier test bench calibration records. | F2: [APPROVED] | compromise_tier_1 | 19.1 (a) Direct, Line-Stoppage & Airworthiness Recall Liability: Seller's liability for general direct damages and final assembly line-stoppage shall be capped at two hundred percent (200%) of the total Purchase Order value ($90M), provided that liability for Fleet Airworthiness Directive (`AD`) recall, gross negligence, willful misconduct, and §24 IP indemnification shall remain strictly uncapped. 24.1 (b) Intellectual Property Indemnification: Seller shall defend, indemnify, and hold harmless Cymbal Aerospace and its airline customers against all third-party intellectual property infringement claims including system-level avionics bus integration, except where such claim arises solely from Cymbal Aerospace's proprietary flight control bus specifications. | G2: [APPROVED] | custom_harmonized | 4.1 (a) Importer of Record & Customs Clearance: Seller shall act as Importer of Record for all imported sub-tier components, raw aerospace titanium forgings, and radiation-hardened semiconductor wafers. (b) Tariff & Duty Allocation: All unit prices in Statement of Work (`SOW-AV-8921`) Schedule A are DDP (Incoterms 2020) Cymbal Aerospace Everett/Renton facility. Any verified new Section 232/301 tariff increase exceeding 5.0% on raw titanium forgings or semiconductor wafers shall be shared 50/50 between Cymbal Aerospace and Seller, strictly capped at a maximum aggregate adjustment of 2.0% of the GP1 §3.1 Firm-Fixed-Price SOW unit price. | H2: [APPROVED] | hold_firm | 3.2 (a) CUI Safeguards & NIST SP 800-171 Rev 2 Compliance: Seller shall maintain an accredited Cybersecurity Maturity Model Certification (`CMMC 2.0 Level 2`) posture and implement all 110 security controls in `NIST SP 800-171 Rev 2` across all engineering networks storing or processing Cymbal Aerospace Covered Defense Information (`CDI`), Controlled Unclassified Information (`CUI`), or `FCC-900` flight control source code. (b) Mandatory Cyber Incident Reporting & Forensics: Pursuant to `DoD DFARS 252.204-7012`, Seller shall report any cybersecurity incident affecting Cymbal Aerospace CDI or technical data to Buyer's Cyber Security Operations Center (`CSOC`) and the DoD DIBNet portal within seventy-two (72) hours of discovery, preserve affected system media for ninety (90) days, and provide raw forensic log images and malware telemetry upon request. | I2: 2 | J2: READY_FOR_DISPATCH
A3: BA-2026-TR-5510 | B3: Vanguard Thrust Systems Corp. | C3: 777X / 787 Thrust Reverser Actuators (TRA-500) | D3: 38000000 | E3: [APPROVED] | hold_firm | 12.2 Seller warrants all TRA-500 Thrust Reverser Actuator assemblies against defects in hydraulic seals, ballscrews, and workmanship for thirty-six (36) months from initial aircraft delivery to Buyer's airline customer. Buyer and FAA representatives may conduct unannounced source inspections at Seller's facility at any time to verify AS9100 Rev D and FAA 14 CFR Part 21.140 production airworthiness compliance. | F3: [CONFLICT] | compromise_tier_1 | 19.1 Seller's aggregate liability for direct damages, nacelle line-stoppage, and thrust reverser airworthiness recall costs shall not exceed one hundred fifty percent (150% / 1.5x) of total Purchase Order value ($57,000,000), with a 2.5x ($95,000,000) Super-Cap and uncapped carveouts for IP indemnification (§24), flight-safety Airworthiness Directives, and DFARS cybersecurity obligations. | G3: [APPROVED] | compromise_tier_1 | 4.1 All TRA-500 unit prices are exclusive of any new Section 232/301 tariffs on specialty Inconel/maraging steel actuator forgings exceeding five percent (5%), which shall be shared 50/50 capped at 2.0% ($760,000) of PO value. | H3: [APPROVED] | hold_firm | 3.2 Seller shall maintain NIST SP 800-171 controls for all TRA-500 digital test benches and report any cybersecurity incident affecting Covered Defense Information within seventy-two (72) hours of discovery, and provide forensic log images upon request. | I3: 1.5 | J3: CONFLICT_DETECTED
A4: BA-2026-LG-7740 | B4: Meridian Landing Gear Corp. | C4: 787-10 Titanium Main Landing Gear Assemblies (TLG-800) | D4: 52000000 | E4: [APPROVED] | hold_firm | 12.2 Seller warrants all TLG-800 Titanium Main Landing Gear Assemblies against structural fatigue, forging inclusions, and defects in workmanship for thirty-six (36) months from initial aircraft delivery to Buyer's airline customer. Buyer and FAA representatives may conduct unannounced source inspections at Seller's forge and machining facilities at any time to verify AS9100 Rev D and FAA 14 CFR Part 21.140 primary structural airworthiness compliance. | F4: [APPROVED] | compromise_tier_1 | 19.1 Seller's liability for direct damages, final assembly line-stoppage, and TLG-800 landing gear Airworthiness Directive recall costs shall not exceed one hundred percent (100%) of the total Purchase Order value ($52,000,000). 24.1 Seller shall indemnify Buyer against all third-party intellectual property infringement claims except where such claim arises from combination of TLG-800 assemblies with Buyer airframe hydraulic systems. | G4: [APPROVED] | compromise_tier_1 | 4.1 All TLG-800 unit prices are exclusive of any new or increased Section 232/301 tariffs on VSMPO/European titanium billet forgings exceeding five percent (5%), which shall be passed through 100% to Buyer. | H4: [APPROVED] | hold_firm | 3.2 Seller shall maintain NIST SP 800-171 controls for all CNC 5-axis machining cells and report any cybersecurity incident affecting Covered Defense Information or TLG-800 technical data within seventy-two (72) hours of discovery, and provide forensic log images upon request. | I4: 2 | J4: READY_FOR_DISPATCH
A5: PORTFOLIO SUMMARY | B5: =COUNTA(A2:A4) | C5: 3 Tier-1 Aerospace Programs (FCC-900 / TRA-500 / TLG-800) | D5: =SUM(D2:D4) | E5: =COUNTIF(E2:E4,"*APPROVED*") | F5: =COUNTIF(F2:F4,"*APPROVED*") | G5: =COUNTIF(G2:G4,"*APPROVED*") | H5: =COUNTIF(H2:H4,"*APPROVED*") | I5: =AVERAGE(I2:I4) | J5: =COUNTIF(J2:J4,"READY_FOR_DISPATCH")
